threedi_settings/__init__.py
threedi_settings/mappings.py
threedi_settings/models.py
threedi_settings/threedimodel_config.py
threedi_settings/commands/__init__.py
threedi_settings/commands/export_legacy_settings.py
threedi_settings/commands/global_settings.py
threedi_settings/commands/helpers.py
threedi_settings/http/__init__.py
threedi_settings/http/api_clients.py
threedi_settings/http/helpers.py
threedi_settings/http/output.py
threedi_settings/plain/__init__.py
threedi_settings/plain/output.py
threedi_settings/pretty/__init__.py
threedi_settings/pretty/output/__init__.py
threedi_settings/pretty/output/global_settings.py
threedi_settings/pretty/output/http.py
threedi_settings-0.0.6.dist-info/AUTHORS.rst
threedi_settings-0.0.6.dist-info/LICENSE
threedi_settings-0.0.6.dist-info/METADATA
threedi_settings-0.0.6.dist-info/WHEEL
threedi_settings-0.0.6.dist-info/entry_points.txt
threedi_settings-0.0.6.dist-info/top_level.txt
threedi_settings-0.0.6.dist-info/RECORD
