Metadata-Version: 2.1
Name: threedi-settings
Version: 0.0.6
Summary: Export legacy 3Di model settings to the 3Di API V3
Home-page: https://github.com/nens/threedi-settings
Author: Lars Claussen
Author-email: claussen.lars@nelen-schuurmans.nl
License: MIT license
Keywords: threedi_settings
Platform: UNKNOWN
Classifier: Development Status :: 2 - Pre-Alpha
Classifier: Intended Audience :: Developers
Classifier: License :: OSI Approved :: MIT License
Classifier: Natural Language :: English
Classifier: Programming Language :: Python :: 3
Classifier: Programming Language :: Python :: 3.7
Classifier: Programming Language :: Python :: 3.8
Classifier: Programming Language :: Python :: 3.9
Requires-Python: >=3.7
Provides-Extra: api
Requires-Dist: threedi-api-client (>3.0.24) ; extra == 'api'
Provides-Extra: cmd
Requires-Dist: typer (>=0.3.2) ; extra == 'cmd'
Requires-Dist: rich (>=10.1.0) ; extra == 'cmd'
Requires-Dist: PyYAML (>=5.1) ; extra == 'cmd'
